POpCan/POpCan.py
POpCan/__init__.py
POpCan/data/Example.csv
POpCan-0.7.9.dist-info/METADATA
POpCan-0.7.9.dist-info/WHEEL
POpCan-0.7.9.dist-info/top_level.txt
POpCan-0.7.9.dist-info/RECORD
