Metadata-Version: 2.1
Name: POpCan
Version: 0.7.9
Summary: Percentage Overlap Tool
Maintainer-email: Pravallika Govada <pravallika2606g@gmail.com>
License: BSD-2-Clause
Requires-Python: >=3.9
Requires-Dist: pandas>=1.0.0
